conscious/__init__.py
conscious/skills/__init__.py
conscious/skills/literacy.py
senses/__init__.py
senses/keystrokes.py
bot_alice-0.0.1.dist-info/LICENCE
bot_alice-0.0.1.dist-info/METADATA
bot_alice-0.0.1.dist-info/WHEEL
bot_alice-0.0.1.dist-info/top_level.txt
bot_alice-0.0.1.dist-info/RECORD
