Metadata-Version: 2.1
Name: bot-alice
Version: 0.0.1
Summary: A program to run a robot
Home-page: https://github.com/kennedyshead/ALICE
Author: Magnus Knutas
Author-email: magnusknutas@gmail.com
Project-URL: Bug Tracker, https://github.com/kennedyshead/ALICE/issues
Classifier: Programming Language :: Python :: 3
Classifier: License :: OSI Approved :: MIT License
Classifier: Operating System :: OS Independent
Requires-Python: >=3.6
License-File: LICENCE
